graph_ragu-1.0.3.dist-info/licenses/LICENSE
ragu/__init__.py
ragu/chunker/__init__.py
ragu/chunker/base_chunker.py
ragu/chunker/chunkers.py
ragu/chunker/types.py
ragu/common/__init__.py
ragu/common/base.py
ragu/common/batch_generator.py
ragu/common/decorator.py
ragu/common/env.py
ragu/common/global_parameters.py
ragu/common/logger.py
ragu/common/prompts/__init__.py
ragu/common/prompts/default_models.py
ragu/common/prompts/default_templates.py
ragu/common/prompts/prompt_storage.py
ragu/embedder/__init__.py
ragu/embedder/base_embedder.py
ragu/embedder/local_embedders.py
ragu/embedder/openai_embedder.py
ragu/graph/__init__.py
ragu/graph/artifacts_summarizer.py
ragu/graph/community_summarizer.py
ragu/graph/graph_builder_pipeline.py
ragu/graph/knowledge_graph.py
ragu/graph/types.py
ragu/llm/__init__.py
ragu/llm/base_llm.py
ragu/llm/openai_client.py
ragu/search_engine/__init__.py
ragu/search_engine/base_engine.py
ragu/search_engine/bfs_search.py
ragu/search_engine/global_search.py
ragu/search_engine/local_search.py
ragu/search_engine/search_functional.py
ragu/search_engine/types.py
ragu/storage/__init__.py
ragu/storage/base_storage.py
ragu/storage/index.py
ragu/storage/graph_storage_adapters/memgraph_adapter.py
ragu/storage/graph_storage_adapters/networkx_adapter.py
ragu/storage/kv_storage_adapters/__init__.py
ragu/storage/kv_storage_adapters/json_storage.py
ragu/storage/kv_storage_adapters/redis_adapter.py
ragu/storage/vdb_storage_adapters/memgraph_vector.py
ragu/storage/vdb_storage_adapters/nano_vdb.py
ragu/storage/vdb_storage_adapters/qdrant.py
ragu/triplet/__init__.py
ragu/triplet/base_artifact_extractor.py
ragu/triplet/llm_artifact_extractor.py
ragu/triplet/ragu_lm_artifact_extractor.py
ragu/triplet/types.py
ragu/utils/__init__.py
ragu/utils/ragu_utils.py
ragu/utils/token_truncation.py
graph_ragu-1.0.3.dist-info/METADATA
graph_ragu-1.0.3.dist-info/WHEEL
graph_ragu-1.0.3.dist-info/top_level.txt
graph_ragu-1.0.3.dist-info/RECORD
