Metadata-Version: 2.4
Name: graph_ragu
Version: 1.0.3
Summary: GraphRAG system
Requires-Python: >=3.10
License-File: LICENSE
Requires-Dist: aiolimiter>=1.2.1
Requires-Dist: graspologic>=3.4.4
Requires-Dist: instructor>=1.11.3
Requires-Dist: loguru>=0.7.3
Requires-Dist: nano-vectordb>=0.0.4.3
Requires-Dist: networkx>=3.4.2
Requires-Dist: nltk>=3.9.2
Requires-Dist: numpy>=1.26.4
Requires-Dist: openai>=1.109.1
Requires-Dist: pandas>=2.3.3
Requires-Dist: pandas-stubs==2.3.2.250926
Requires-Dist: pydantic>=2.11.10
Requires-Dist: pydantic-settings>=2.11.0
Requires-Dist: pytest>=8.4.2
Requires-Dist: razdel>=0.5.0
Requires-Dist: tenacity>=9.1.2
Requires-Dist: tiktoken>=0.11.0
Requires-Dist: tqdm>=4.67.1
Provides-Extra: local
Requires-Dist: sentence-transformers>=5.1.1; extra == "local"
Requires-Dist: transformers>=4.57.0; extra == "local"
Dynamic: license-file
